nsec3_hash/__init__.py
nsec3_hash/cli.py
nsec3_hash-1.0.0.dist-info/METADATA
nsec3_hash-1.0.0.dist-info/WHEEL
nsec3_hash-1.0.0.dist-info/entry_points.txt
nsec3_hash-1.0.0.dist-info/licenses/LICENSE.TXT
nsec3_hash-1.0.0.dist-info/RECORD
